agentsystems_notary/__init__.py
agentsystems_notary/arweave.py
agentsystems_notary/config.py
agentsystems_notary/core.py
agentsystems_notary/crewai_adapter.py
agentsystems_notary/langchain_adapter.py
agentsystems_notary/signing.py
agentsystems_notary/storage.py
agentsystems_notary-0.4.1.dist-info/licenses/LICENSE
agentsystems_notary-0.4.1.dist-info/METADATA
agentsystems_notary-0.4.1.dist-info/WHEEL
agentsystems_notary-0.4.1.dist-info/top_level.txt
agentsystems_notary-0.4.1.dist-info/RECORD
