Metadata-Version: 2.4
Name: agentsystems-notary
Version: 0.4.1
Summary: Cryptographic notarization SDK for LLM interactions
Author-email: AgentSystems <support@agentsystems.ai>
License-Expression: Apache-2.0
Requires-Python: >=3.11
License-File: LICENSE
Requires-Dist: boto3>=1.34.0
Requires-Dist: httpx>=0.25.0
Requires-Dist: jcs>=0.2.1
Requires-Dist: cryptography>=41.0.0
Requires-Dist: requests>=2.28.0
Provides-Extra: langchain
Requires-Dist: langchain-core>=0.1.0; extra == "langchain"
Provides-Extra: crewai
Requires-Dist: crewai>=0.1.0; extra == "crewai"
Provides-Extra: all
Requires-Dist: langchain-core>=0.1.0; extra == "all"
Requires-Dist: crewai>=0.1.0; extra == "all"
Provides-Extra: dev
Requires-Dist: pytest>=7.0; extra == "dev"
Requires-Dist: pytest-cov>=4.0; extra == "dev"
Requires-Dist: black>=23.0; extra == "dev"
Requires-Dist: ruff>=0.1.0; extra == "dev"
Requires-Dist: mypy>=1.5; extra == "dev"
Requires-Dist: types-requests>=2.28.0; extra == "dev"
Requires-Dist: build; extra == "dev"
Requires-Dist: twine; extra == "dev"
Requires-Dist: pip-licenses>=4.0.0; extra == "dev"
Provides-Extra: license-files
Requires-Dist: LICENSE; extra == "license-files"
Dynamic: license-file
